Metadata-Version: 2.1
Name: mygradesproject
Version: 0.0
Summary: This is a grades calculator I made for my project
Author-email: aghahanzalahahmad@gmail.com
License: UNKNOWN
Platform: UNKNOWN
License-File: license.txt
